ci_tools_roz/__init__.py
ci_tools_roz/ci_credentials.py
ci_tools_roz/ci_docker.py
ci_tools_roz/recover_s3.py
ci_tools_roz/version.py
ci_tools_roz/vpc_peering.py
ci_tools-roz-4.1.2b73+45d2cef8.dist-info/METADATA
ci_tools_roz-4.1.2b73+45d2cef8.dist-info/WHEEL
ci_tools_roz-4.1.2b73+45d2cef8.dist-info/entry_points.txt
ci_tools_roz-4.1.2b73+45d2cef8.dist-info/top_level.txt
ci_tools_roz-4.1.2b73+45d2cef8.dist-info/RECORD
