Metadata-Version: 2.1
Name: ci-tools-roz
Version: 4.1.2b73
Summary: CI tool scripts
Home-page: https://github.com/rozettatechnology/ci_tools
Author: Rozetta Technology
Author-email: info@rozettatechnology.com
License: UNKNOWN
Platform: UNKNOWN
Classifier: Development Status :: 5 - Production/Stable
Classifier: Environment :: Console
Classifier: Intended Audience :: Developers
Classifier: License :: Other/Proprietary License
Classifier: Natural Language :: English
Classifier: Operating System :: Unix
Classifier: Programming Language :: Python
Classifier: Topic :: Software Development
Requires-Dist: gitpython
Requires-Dist: pycli
Requires-Dist: boto3
Requires-Dist: pyyaml
Requires-Dist: docker
